test_run_dir/acal_lab05.Hw1.TrafficLight_pTest2082851956/TrafficLight_p.v
module TrafficLight_p(
  input        clock,
  input        reset,
  input        io_P_button,
  output [1:0] io_H_traffic,
  output [1:0] io_V_traffic,
  output [1:0] io_P_traffic,
  output [4:0] io_timer
);
`ifdef RANDOMIZE_REG_INIT
  reg [31:0] _RAND_0;
  reg [31:0] _RAND_1;
`endif // RANDOMIZE_REG_INIT
  reg [2:0] state; // @[TrafficLight_p.scala 25:22]
  reg [3:0] cntReg; // @[TrafficLight_p.scala 29:23]
  wire  cntDone = cntReg == 4'h0; // @[TrafficLight_p.scala 31:21]
  wire  _T_11 = 3'h1 == state; // @[Conditional.scala 37:30]
  wire  _T_12 = 3'h2 == state; // @[Conditional.scala 37:30]
  wire  _T_13 = 3'h3 == state; // @[Conditional.scala 37:30]
  wire  _T_14 = 3'h4 == state; // @[Conditional.scala 37:30]
  wire  _T_15 = 3'h5 == state; // @[Conditional.scala 37:30]
  wire [1:0] _GEN_15 = _T_15 ? 2'h2 : 2'h0; // @[Conditional.scala 39:67 TrafficLight_p.scala 107:15 TrafficLight_p.scala 76:11]
  wire [1:0] _GEN_18 = _T_14 ? 2'h0 : _GEN_15; // @[Conditional.scala 39:67 TrafficLight_p.scala 101:15]
  wire [1:0] _GEN_22 = _T_13 ? 2'h1 : _GEN_18; // @[Conditional.scala 39:67 TrafficLight_p.scala 95:15]
  wire [1:0] _GEN_26 = _T_12 ? 2'h0 : _GEN_22; // @[Conditional.scala 39:67 TrafficLight_p.scala 89:15]
  wire [1:0] cntMode = _T_11 ? 2'h1 : _GEN_26; // @[Conditional.scala 40:58 TrafficLight_p.scala 83:15]
  wire [2:0] _GEN_0 = cntMode == 2'h1 ? 3'h2 : 3'h4; // @[TrafficLight_p.scala 36:32 TrafficLight_p.scala 37:14 TrafficLight_p.scala 39:14]
  wire [2:0] _GEN_1 = cntMode == 2'h0 ? 3'h6 : _GEN_0; // @[TrafficLight_p.scala 34:26 TrafficLight_p.scala 35:14]
  wire [3:0] _T_4 = cntReg - 4'h1; // @[TrafficLight_p.scala 42:22]
  wire  _T_5 = 3'h0 == state; // @[Conditional.scala 37:30]
  wire [2:0] _GEN_3 = cntDone ? 3'h2 : state; // @[TrafficLight_p.scala 55:23 TrafficLight_p.scala 55:30 TrafficLight_p.scala 25:22]
  wire [2:0] _GEN_4 = cntDone ? 3'h3 : state; // @[TrafficLight_p.scala 58:23 TrafficLight_p.scala 58:30 TrafficLight_p.scala 25:22]
  wire [2:0] _GEN_5 = cntDone ? 3'h4 : state; // @[TrafficLight_p.scala 61:23 TrafficLight_p.scala 61:30 TrafficLight_p.scala 25:22]
  wire [2:0] _GEN_6 = cntDone ? 3'h1 : state; // @[TrafficLight_p.scala 64:23 TrafficLight_p.scala 64:30 TrafficLight_p.scala 25:22]
  wire [2:0] _GEN_9 = _T_14 ? _GEN_6 : state; // @[Conditional.scala 39:67]
  wire [2:0] _GEN_10 = _T_13 ? _GEN_5 : _GEN_9; // @[Conditional.scala 39:67]
  wire [2:0] _GEN_11 = _T_12 ? _GEN_4 : _GEN_10; // @[Conditional.scala 39:67]
  wire [1:0] _GEN_17 = _T_15 ? 2'h3 : 2'h0; // @[Conditional.scala 39:67 TrafficLight_p.scala 110:20 TrafficLight_p.scala 79:16]
  wire  _GEN_19 = _T_14 | _T_15; // @[Conditional.scala 39:67 TrafficLight_p.scala 102:20]
  wire [1:0] _GEN_20 = _T_14 ? 2'h2 : {{1'd0}, _T_15}; // @[Conditional.scala 39:67 TrafficLight_p.scala 103:20]
  wire [1:0] _GEN_21 = _T_14 ? 2'h1 : _GEN_17; // @[Conditional.scala 39:67 TrafficLight_p.scala 104:20]
  wire  _GEN_23 = _T_13 | _GEN_19; // @[Conditional.scala 39:67 TrafficLight_p.scala 96:20]
  wire [1:0] _GEN_24 = _T_13 ? 2'h3 : _GEN_20; // @[Conditional.scala 39:67 TrafficLight_p.scala 97:20]
  wire [1:0] _GEN_25 = _T_13 ? 2'h1 : _GEN_21; // @[Conditional.scala 39:67 TrafficLight_p.scala 98:20]
  wire [1:0] _GEN_27 = _T_12 ? 2'h2 : {{1'd0}, _GEN_23}; // @[Conditional.scala 39:67 TrafficLight_p.scala 90:20]
  wire [1:0] _GEN_28 = _T_12 ? 2'h1 : _GEN_24; // @[Conditional.scala 39:67 TrafficLight_p.scala 91:20]
  wire [1:0] _GEN_29 = _T_12 ? 2'h1 : _GEN_25; // @[Conditional.scala 39:67 TrafficLight_p.scala 92:20]
  assign io_H_traffic = _T_11 ? 2'h3 : _GEN_27; // @[Conditional.scala 40:58 TrafficLight_p.scala 84:20]
  assign io_V_traffic = _T_11 ? 2'h1 : _GEN_28; // @[Conditional.scala 40:58 TrafficLight_p.scala 85:20]
  assign io_P_traffic = _T_11 ? 2'h1 : _GEN_29; // @[Conditional.scala 40:58 TrafficLight_p.scala 86:20]
  assign io_timer = {{1'd0}, cntReg}; // @[TrafficLight_p.scala 114:12]
  always @(posedge clock) begin
    if (reset) begin // @[TrafficLight_p.scala 25:22]
      state <= 3'h0; // @[TrafficLight_p.scala 25:22]
    end else if (io_P_button) begin // @[TrafficLight_p.scala 47:20]
      state <= 3'h5; // @[TrafficLight_p.scala 48:11]
    end else if (_T_5) begin // @[Conditional.scala 40:58]
      state <= 3'h1; // @[TrafficLight_p.scala 52:15]
    end else if (_T_11) begin // @[Conditional.scala 39:67]
      state <= _GEN_3;
    end else begin
      state <= _GEN_11;
    end
    if (reset) begin // @[TrafficLight_p.scala 29:23]
      cntReg <= 4'h0; // @[TrafficLight_p.scala 29:23]
    end else if (cntDone) begin // @[TrafficLight_p.scala 33:16]
      cntReg <= {{1'd0}, _GEN_1};
    end else begin
      cntReg <= _T_4; // @[TrafficLight_p.scala 42:12]
    end
  end
// Register and memory initialization
`ifdef RANDOMIZE_GARBAGE_ASSIGN
`define RANDOMIZE
`endif
`ifdef RANDOMIZE_INVALID_ASSIGN
`define RANDOMIZE
`endif
`ifdef RANDOMIZE_REG_INIT
`define RANDOMIZE
`endif
`ifdef RANDOMIZE_MEM_INIT
`define RANDOMIZE
`endif
`ifndef RANDOM
`define RANDOM $random
`endif
`ifdef RANDOMIZE_MEM_INIT
  integer initvar;
`endif
`ifndef SYNTHESIS
`ifdef FIRRTL_BEFORE_INITIAL
`FIRRTL_BEFORE_INITIAL
`endif
initial begin
  `ifdef RANDOMIZE
    `ifdef INIT_RANDOM
      `INIT_RANDOM
    `endif
    `ifndef VERILATOR
      `ifdef RANDOMIZE_DELAY
        #`RANDOMIZE_DELAY begin end
      `else
        #0.002 begin end
      `endif
    `endif
`ifdef RANDOMIZE_REG_INIT
  _RAND_0 = {1{`RANDOM}};
  state = _RAND_0[2:0];
  _RAND_1 = {1{`RANDOM}};
  cntReg = _RAND_1[3:0];
`endif // RANDOMIZE_REG_INIT
  `endif // RANDOMIZE
end // initial
`ifdef FIRRTL_AFTER_INITIAL
`FIRRTL_AFTER_INITIAL
`endif
`endif // SYNTHESIS
endmodule

test_run_dir/acal_lab05.Hw1.TrafficLight_pTest2082851956/TrafficLight_p.vcd
$version Generated by VerilatedVcd $end
$date Tue Mar 19 22:05:17 2024
 $end
$timescale   1ns $end

 $scope module TOP $end
  $var wire  1 C clock $end
  $var wire  2 [ io_H_traffic [1:0] $end
  $var wire  1 S io_P_button $end
  $var wire  2 k io_P_traffic [1:0] $end
  $var wire  2 c io_V_traffic [1:0] $end
  $var wire  5 s io_timer [4:0] $end
  $var wire  1 K reset $end
  $scope module TrafficLight_p $end
   $var wire  1 C clock $end
   $var wire  1 ; cntDone $end
   $var wire  2 # cntMode [1:0] $end
   $var wire  4 3 cntReg [3:0] $end
   $var wire  2 [ io_H_traffic [1:0] $end
   $var wire  1 S io_P_button $end
   $var wire  2 k io_P_traffic [1:0] $end
   $var wire  2 c io_V_traffic [1:0] $end
   $var wire  5 s io_timer [4:0] $end
   $var wire  1 K reset $end
   $var wire  3 + state [2:0] $end
  $upscope $end
 $upscope $end
$enddefinitions $end


#0
b00 #
b000 +
b0000 3
1;
0C
1K
0S
b00 [
b00 c
b00 k
b00000 s
#1
1C
#2
0C
#3
1C
#4
0C
#5
1C
#6
0C
#7
1C
#8
0C
#9
1C
#10
0C
0K
#11
b01 #
b001 +
b0110 3
0;
1C
b11 [
b01 c
b01 k
b00110 s
#12
0C
#13
b0101 3
1C
b00101 s
#14
0C
#15
b0100 3
1C
b00100 s
#16
0C
#17
b0011 3
1C
b00011 s
#18
0C
#19
b0010 3
1C
b00010 s
#20
0C
#21
b0001 3
1C
b00001 s
#22
0C
#23
b0000 3
1;
1C
b00000 s
#24
0C
#25
b00 #
b010 +
b0010 3
0;
1C
b10 [
b00010 s
#26
0C
#27
b0001 3
1C
b00001 s
#28
0C
#29
b0000 3
1;
1C
b00000 s
#30
0C
#31
b01 #
b011 +
b0110 3
0;
1C
b01 [
b11 c
b00110 s
#32
0C
#33
b0101 3
1C
b00101 s
#34
0C
#35
b0100 3
1C
b00100 s
#36
0C
#37
b0011 3
1C
b00011 s
#38
0C
#39
b0010 3
1C
b00010 s
#40
0C
#41
b0001 3
1C
b00001 s
#42
0C
#43
b0000 3
1;
1C
b00000 s
#44
0C
#45
b00 #
b100 +
b0010 3
0;
1C
b10 c
b00010 s
#46
0C
#47
b0001 3
1C
b00001 s
#48
0C
#49
b0000 3
1;
1C
b00000 s
#50
0C
#51
b01 #
b001 +
b0110 3
0;
1C
b11 [
b01 c
b00110 s
#52
0C
#53
b0101 3
1C
b00101 s
#54
0C
#55
b0100 3
1C
b00100 s
#56
0C
#57
b0011 3
1C
b00011 s
#58
0C
#59
b0010 3
1C
b00010 s
#60
0C
#61
b0001 3
1C
b00001 s
#62
0C
#63
b0000 3
1;
1C
b00000 s
#64
0C
#65
b00 #
b010 +
b0010 3
0;
1C
b10 [
b00010 s
#66
0C
#67
b0001 3
1C
b00001 s
#68
0C
#69
b0000 3
1;
1C
b00000 s
#70
0C
#71
b01 #
b011 +
b0110 3
0;
1C
b01 [
b11 c
b00110 s
#72
0C
#73
b0101 3
1C
b00101 s
#74
0C
#75
b0100 3
1C
b00100 s
#76
0C
#77
b0011 3
1C
b00011 s
#78
0C
#79
b0010 3
1C
b00010 s
#80
0C
#81
b0001 3
1C
b00001 s
#82
0C
#83
b0000 3
1;
1C
b00000 s
#84
0C
#85
b00 #
b100 +
b0010 3
0;
1C
b10 c
b00010 s
#86
0C
#87
b0001 3
1C
b00001 s
#88
0C
1S
#89
b10 #
b101 +
b0000 3
1;
1C
b01 c
b11 k
b00000 s
#90
0C
0S
#91
b0100 3
0;
1C
b00100 s
#92
0C
#93
b0011 3
1C
b00011 s
#94
0C
#95
b0010 3
1C
b00010 s
#96
0C
#97
b0001 3
1C
b00001 s
#98
0C
#99
b0000 3
1;
1C
b00000 s
#100
0C
#101
b0100 3
0;
1C
b00100 s
#102
0C
#103
b0011 3
1C
b00011 s
#104
0C
#105
b0010 3
1C
b00010 s
#106
0C
#107
b0001 3
1C
b00001 s
#108
0C
#109
b0000 3
1;
1C
b00000 s
#110
0C
#111
b0100 3
0;
1C
b00100 s
#112
0C
#113
b0011 3
1C
b00011 s
#114
0C
#115
b0010 3
1C
b00010 s
#116
0C
#117
b0001 3
1C
b00001 s
#118
0C
#119
b0000 3
1;
1C
b00000 s
#120
0C
#121
b0100 3
0;
1C
b00100 s
#122
0C
#123
b0011 3
1C
b00011 s
#124
0C
1S
#125
b0010 3
1C
b00010 s
#126
0C
0S
#127
b0001 3
1C
b00001 s
#128
0C
#129
b0000 3
1;
1C
b00000 s
#130
0C
#131
b0100 3
0;
1C
b00100 s
#132
0C
#133
b0011 3
1C
b00011 s
#134
0C
#135
b0010 3
1C
b00010 s
#136
0C
#137
b0001 3
1C
b00001 s
#138
0C
#139
b0000 3
1;
1C
b00000 s
#140
0C
#141
b0100 3
0;
1C
b00100 s
#142
0C
#143
b0011 3
1C
b00011 s
#144
0C
#145
b0010 3
1C
b00010 s
#146
0C
#147
b0001 3
1C
b00001 s
#148
0C
#149
b0000 3
1;
1C
b00000 s
#150
0C
#151
b0100 3
0;
1C
b00100 s
#152
0C
#153
b0011 3
1C
b00011 s
#154
0C
#155
b0010 3
1C
b00010 s
#156
0C
#157
b0001 3
1C
b00001 s
#158
0C
#159
b0000 3
1;
1C
b00000 s
#160
0C
#161
b0100 3
0;
1C
b00100 s
#162
0C
#163
b0011 3
1C
b00011 s
#164
0C
#165
b0010 3
1C
b00010 s
#166
0C
#167
b0001 3
1C
b00001 s
#168
0C
#169
b0000 3
1;
1C
b00000 s
#170
0C
#171
b0100 3
0;
1C
b00100 s
#172
0C
#173
b0011 3
1C
b00011 s
#174
0C
#175
b0010 3
1C
b00010 s
#176
0C
#177
b0001 3
1C
b00001 s
#178
0C
#179
b0000 3
1;
1C
b00000 s
#180
0C
#181
b0100 3
0;
1C
b00100 s
#182
0C
#183
b0011 3
1C
b00011 s
#184
0C
#185
b0010 3
1C
b00010 s
#186
0C
#187
b0001 3
1C
b00001 s
#188
0C
#189
b0000 3
1;
1C
b00000 s
#190
0C
#191
b0100 3
0;
1C
b00100 s
#192
0C
#193
b0011 3
1C
b00011 s
#194
0C
#195
b0010 3
1C
b00010 s
#196
0C
#197
b0001 3
1C
b00001 s
#198
0C
#199
b0000 3
1;
1C
b00000 s
#200
0C
#201
b0100 3
0;
1C
b00100 s
#202
0C
#203
b0011 3
1C
b00011 s
#204
0C
#205
b0010 3
1C
b00010 s
#206
0C
#207
b0001 3
1C
b00001 s
#208
0C
#209
b0000 3
1;
1C
b00000 s
#210
0C
#211
b0100 3
0;
1C
b00100 s
#212
0C
#213
b0011 3
1C
b00011 s
#214
0C
#215
b0010 3
1C
b00010 s
#216
0C
#217
b0001 3
1C
b00001 s
#218
0C
#219
b0000 3
1;
1C
b00000 s
#220
0C
#221
b0100 3
0;
1C
b00100 s
#222
0C
#223
b0011 3
1C
b00011 s
#224
0C
#225
b0010 3
1C
b00010 s
